django_wsgi_view-0.0.1.dist-info/DESCRIPTION.rst
django_wsgi_view-0.0.1.dist-info/METADATA
django_wsgi_view-0.0.1.dist-info/RECORD
django_wsgi_view-0.0.1.dist-info/WHEEL
django_wsgi_view-0.0.1.dist-info/metadata.json
django_wsgi_view-0.0.1.dist-info/top_level.txt
wsgi_view/__init__.py
