Metadata-Version: 2.0
Name: django-wsgi-view
Version: 0.0.1
Summary: Embed WSGI application as Django view.
Home-page: https://github.com/ratson/django-wsgi-view
Author: Ratson
Author-email: contact@ratson.name
License: UNKNOWN
Platform: UNKNOWN
Classifier: Development Status :: 2 - Pre-Alpha
Classifier: License :: OSI Approved :: MIT License
Classifier: Programming Language :: Python
Classifier: Programming Language :: Python :: 3
Classifier: Programming Language :: Python :: 3.6
